DwfInterface/DigiScope.py
DwfInterface/DigiScopeGraph.py
DwfInterface/Enumerate.py
DwfInterface/__init__.py
DwfInterface/dwfconstants.py
DwfInterface/resource/__init__.py
DwfInterface/tests/__init__.py
DwfInterface/tests/test_settingtable.py
DwfInterface/tests/test_with_json.py
dwfpy_ux-0.3.11.dist-info/LICENSE
dwfpy_ux-0.3.11.dist-info/METADATA
dwfpy_ux-0.3.11.dist-info/WHEEL
dwfpy_ux-0.3.11.dist-info/top_level.txt
dwfpy_ux-0.3.11.dist-info/RECORD
