Metadata-Version: 2.1
Name: dwfpy-ux
Version: 0.3.11
Summary: Digilent Waveforms API facade with optional UIX
Home-page: https://github.com/snmendoza/dwfpy-ux
Author: Sean Mendoza
Author-email: sean.mendoza@mac.com
License: UNKNOWN
Platform: UNKNOWN
Classifier: Programming Language :: Python :: 3
Classifier: License :: OSI Approved :: MIT License
Classifier: Operating System :: OS Independent
Requires-Python: >=3.6,<3.13
License-File: LICENSE
Requires-Dist: numpy (<2.0.0)
Requires-Dist: pandas (>=1.3.0)
Requires-Dist: PyQt5 (>=5.15.0)
Requires-Dist: pyqtgraph (>=0.13.0)
Requires-Dist: pglive
Requires-Dist: ipython (>=7.0.0)
Requires-Dist: ipywidgets (>=7.0.0)
Requires-Dist: ipykernel (>=6.0.0)
